hivemind_voice_satellite/__init__.py
hivemind_voice_satellite/__main__.py
hivemind_voice_satellite/service.py
hivemind_voice_satellite/version.py
HiveMind_voice_sat-2.0.1.dist-info/LICENSE
HiveMind_voice_sat-2.0.1.dist-info/METADATA
HiveMind_voice_sat-2.0.1.dist-info/WHEEL
HiveMind_voice_sat-2.0.1.dist-info/entry_points.txt
HiveMind_voice_sat-2.0.1.dist-info/top_level.txt
HiveMind_voice_sat-2.0.1.dist-info/RECORD
