Metadata-Version: 2.1
Name: HiveMind-voice-sat
Version: 2.0.1
Summary: Hivemind Voice Satellite
Home-page: https://github.com/OpenJarbas/HiveMind-voice-sat
Author: jarbasAI
Author-email: jarbasai@mailfence.com
License: MIT
Platform: UNKNOWN
Requires-Dist: hivemind-bus-client>=0.0.4a10
Requires-Dist: ovos-audio
Requires-Dist: ovos-dinkum-listener>=0.0.3
Requires-Dist: ovos-microphone-plugin-alsa
Requires-Dist: ovos-vad-plugin-silero
Requires-Dist: ovos-stt-plugin-server
Requires-Dist: ovos-tts-plugin-server
Requires-Dist: ovos-ww-plugin-vosk
Requires-Dist: click
Requires-Dist: hivemind-ggwave
